src/__init__.py
src/server.py
mcp_google_email-0.1.1.dist-info/METADATA
mcp_google_email-0.1.1.dist-info/WHEEL
mcp_google_email-0.1.1.dist-info/top_level.txt
mcp_google_email-0.1.1.dist-info/RECORD
