Metadata-Version: 2.4
Name: mcp-google-email
Version: 0.1.1
Summary: MCP for GMail
Home-page: https://github.com/yourusername/mcp-gmail
Author: Amitesh Gangrade
Author-email: gangradeamitesh@gmail.com
Requires-Python: >=3.10
Requires-Dist: fastapi>=0.68.0
Requires-Dist: google-api-python-client>=2.0.0
Requires-Dist: google-auth-httplib2>=0.1.0
Requires-Dist: google-auth-oauthlib>=0.4.6
Requires-Dist: mcp>=1.0.0
Requires-Dist: pydantic>=1.8.0
Requires-Dist: python-dotenv>=0.19.0
Requires-Dist: uvicorn>=0.15.0
Dynamic: author
Dynamic: author-email
Dynamic: home-page
Dynamic: requires-python
